{
  "formatVersion": 1,
  "database": {
    "version": 61,
    "identityHash": "eaf540c96765f819dd2a4629bcca1584",
    "entities": [
      {
        "tableName": "Wallet",
        "createSql": "CREATE TABLE IF NOT EXISTS `${TABLE_NAME}` (`id` INTEGER PRIMARY KEY AUTOINCREMENT NOT NULL, `mnemonic` TEXT, `pk` TEXT, `address` TEXT NOT NULL)",
        "fields": [
          {
            "fieldPath": "id",
            "columnName": "id",
            "affinity": "INTEGER",
            "notNull": true
          },
          {
            "fieldPath": "mnemonic",
            "columnName": "mnemonic",
            "affinity": "TEXT",
            "notNull": false
          },
          {
            "fieldPath": "pk",
            "columnName": "pk",
            "affinity": "TEXT",
            "notNull": false
          },
          {
            "fieldPath": "address",
            "columnName": "address",
            "affinity": "TEXT",
            "notNull": true
          }
        ],
        "primaryKey": {
          "columnNames": [
            "id"
          ],
          "autoGenerate": true
        },
        "indices": [],
        "foreignKeys": []
      }
    ],
    "views": [],
    "setupQueries": [
      "CREATE TABLE IF NOT EXISTS room_master_table (id INTEGER PRIMARY KEY,identity_hash TEXT)",
      "INSERT OR REPLACE INTO room_master_table (id,identity_hash) VALUES(42, 'eaf540c96765f819dd2a4629bcca1584')"
    ]
  }
}